oops_timeline/__init__.py
oops_timeline/hooks.py
oops_timeline-0.1.0.dist-info/licenses/LICENSE
oops_timeline-0.1.0.dist-info/METADATA
oops_timeline-0.1.0.dist-info/WHEEL
oops_timeline-0.1.0.dist-info/top_level.txt
oops_timeline-0.1.0.dist-info/RECORD
