Metadata-Version: 2.4
Name: oops_timeline
Version: 0.1.0
Summary: Integrate timelines with OOPS error reports.
Home-page: https://launchpad.net/python-oops-timeline
Maintainer: Launchpad Developers
Maintainer-email: launchpad-dev@lists.launchpad.net
Classifier: Development Status :: 2 - Pre-Alpha
Classifier: Intended Audience :: Developers
Classifier: License :: OSI Approved :: GNU Lesser General Public License v3 (LGPLv3)
Classifier: Operating System :: OS Independent
Classifier: Programming Language :: Python
Classifier: Programming Language :: Python :: 3
Classifier: Programming Language :: Python :: 3.8
Requires-Python: >=3.8
License-File: LICENSE
Requires-Dist: oops
Requires-Dist: timeline
Provides-Extra: test
Requires-Dist: testtools; extra == "test"
Dynamic: classifier
Dynamic: description
Dynamic: description-content-type
Dynamic: home-page
Dynamic: license-file
Dynamic: maintainer
Dynamic: maintainer-email
Dynamic: provides-extra
Dynamic: requires-dist
Dynamic: requires-python
Dynamic: summary
